{
  "notes": [
    {
      "title": "Test Title",
      "text": "Test text",
      "id": "32323232"
    },
    {
      "title": "asdfasdf",
      "text": "asdfasdfasdf",
      "id": "a64b39695210f1d3910379de77500f09"
    },
    {
      "title": "asdfasdfa",
      "text": "asdfasdfasdf",
      "id": "a64b39695210f1d3379de77500f09"
    },
    {
      "title": "test",
      "text": "test",
      "id": "19051dd7263c011778807ad0ff37c859"
    },
    {
      "title": "test",
      "text": "tset",
      "id": "19051dd72011778807ad0ff37c859"
    },
    {
      "title": "aqsdfasdf",
      "text": "asdfasdfasdfasdfasdfasdfasdf",
      "id": "08eda2e9ef84439b5604ad8cc1bbe690"
    },
    {
      "title": "test11111",
      "text": "sedfsdfsdf",
      "id": "08eda2e9ef84439b5604ad8cc1bbe690"
    },
    {
      "title": "aSDASD",
      "text": "ASDASDASD",
      "id": "b2019725c8fbf9a52c3ff1c00da73b"
    },
    {
      "title": "ASDASDASDASD",
      "text": "ASDASDASDASD",
      "id": "b201972563c8fbf9a52c3ff1c00da73b"
    },
    {
      "title": "234234",
      "text": "234234234"
    },
    {
      "title": "234234234234234",
      "text": "234234234234234",
      "id": "c38ac9dcee3790b29e9b85650dd55815"
    },
    {
      "title": "1213123",
      "text": "123123123",
      "id": "be36b820b5622c0090b547edfce9c716"
    }
  ]
}